jerde/__init__.py
jerde-0.1.9.dist-info/WHEEL
jerde-0.1.9.dist-info/METADATA
jerde-0.1.9.dist-info/RECORD
