Metadata-Version: 2.1
Name: jerde
Version: 0.1.9
Summary: Json parsing for humans
License: MIT
Keywords: json,parsing,orm,serde
Author-email: vivax3794 <vivax3794@protonmail.com>
Requires-Python: >=3.10
Classifier: 
Classifier: Development Status :: 5 - Production/Stable
Classifier: Intended Audience :: Developers
Classifier: Natural Language :: English
Classifier: Operating System :: OS Independent
Requires-Dist: typing-extensions>=4.3.0
Project-URL: docs, https://vivax3794.github.io/jerde/jerde/
Project-URL: source, https://github.com/vivax3794/jerde
